gog_price_checker/__init__.py
gog_price_checker/__main__.py
gog_price_checker-1.0.0.dist-info/METADATA
gog_price_checker-1.0.0.dist-info/WHEEL
gog_price_checker-1.0.0.dist-info/entry_points.txt
gog_price_checker-1.0.0.dist-info/top_level.txt
gog_price_checker-1.0.0.dist-info/RECORD
