Metadata-Version: 2.1
Name: gog-price-checker
Version: 1.0.0
Summary: A tool to check game prices from GOG API
Home-page: https://github.com/iampopovich/gog_price_checker
Author: Alex
Author-email: iampopovich@example.com
Classifier: Programming Language :: Python :: 3
Classifier: License :: OSI Approved :: MIT License
Classifier: Operating System :: OS Independent
